tech_inspection_service_client/__init__.py
tech_inspection_service_client/api_client.py
tech_inspection_service_client/configuration.py
tech_inspection_service_client/exceptions.py
tech_inspection_service_client/rest.py
tech_inspection_service_client/api/__init__.py
tech_inspection_service_client/api/operators_api.py
tech_inspection_service_client/api/points_api.py
tech_inspection_service_client/models/__init__.py
tech_inspection_service_client/models/error.py
tech_inspection_service_client/models/error_model.py
tech_inspection_service_client/models/problem_details.py
tech_inspection_service_client/models/tech_inspection_operator_query.py
tech_inspection_service_client/models/tech_inspection_operator_status.py
tech_inspection_service_client/models/tech_inspection_point_query.py
tech_inspection_service_client/models/tech_inspection_point_query_query_result.py
tech_inspection_service_client/models/tech_inspection_point_status.py
tech_inspection_service_client-1.0.3.dist-info/METADATA
tech_inspection_service_client-1.0.3.dist-info/WHEEL
tech_inspection_service_client-1.0.3.dist-info/top_level.txt
tech_inspection_service_client-1.0.3.dist-info/RECORD
