Metadata-Version: 2.1
Name: tech-inspection-service-client
Version: 1.0.3
Summary: TechInspection 1.0
Home-page: https://github.com/sravni/techinspection
Author: OpenAPI Generator community
Author-email: team@openapitools.org
License: UNKNOWN
Keywords: OpenAPI,OpenAPI-Generator,TechInspection 1.0
Platform: UNKNOWN
Requires-Dist: urllib3 (>=1.15)
Requires-Dist: six (>=1.10)
Requires-Dist: certifi
Requires-Dist: python-dateutil
